precinct_mapper/__init__.py
precinct_mapper/data/__init__.py
precinct_mapper/data/containers/__init__.py
precinct_mapper/data/containers/region.py
precinct_mapper/data/containers/state.py
precinct_mapper/data/fetcher.py
precinct_mapper/data/parser.py
precinct_mapper/mapper.py
precinct_mapper-0.2.1.dist-info/LICENSE
precinct_mapper-0.2.1.dist-info/METADATA
precinct_mapper-0.2.1.dist-info/WHEEL
precinct_mapper-0.2.1.dist-info/RECORD
