Metadata-Version: 2.1
Name: precinct-mapper
Version: 0.2.1
Summary: A Python Package to preprocess voting precinct and district geodata and make it easy to query. Currently restricted to WA state.
Home-page: https://github.com/clear-vote/precinct-mapper
License: MIT
Keywords: precinct,geodata,geopandas,boundary,districts
Author: Anaya Pandit
Author-email: anaya.pandit7924@gmail.com
Requires-Python: >=3.11.7,<4.0.0
Classifier: License :: OSI Approved :: MIT License
Classifier: Programming Language :: Python :: 3
Classifier: Programming Language :: Python :: 3.12
Requires-Dist: geopandas (>=0.14.2,<0.15.0)
Requires-Dist: requests (>=2.32.3,<3.0.0)
Requires-Dist: typeguard (>=4.2.1,<5.0.0)
Project-URL: Repository, https://github.com/clear-vote/precinct-mapper
